{"frames":{"landscapeTiles_000.png":{"frame":{"x":265,"y":1057,"w":132,"h":83},"spriteSourceSize":{"x":0,"y":0,"w":132,"h":83},"sourceSize":{"w":132,"h":83},"rotated":false,"trimmed":false},"landscapeTiles_001.png":{"frame":{"x":265,"y":1452,"w":132,"h":99},"spriteSourceSize":{"x":0,"y":0,"w":132,"h":99},"sourceSize":{"w":132,"h":99},"rotated":false,"trimmed":false},"landscapeTiles_002.png":{"frame":{"x":265,"y":1369,"w":132,"h":83},"spriteSourceSize":{"x":0,"y":0,"w":132,"h":83},"sourceSize":{"w":132,"h":83},"rotated":false,"trimmed":false},"landscapeTiles_003.png":{"frame":{"x":265,"y":1682,"w":132,"h":83},"spriteSourceSize":{"x":0,"y":0,"w":132,"h":83},"sourceSize":{"w":132,"h":83},"rotated":false,"trimmed":false},"landscapeTiles_004.png":{"frame":{"x":529,"y":1191,"w":132,"h":99},"spriteSourceSize":{"x":0,"y":0,"w":132,"h":99},"sourceSize":{"w":132,"h":99},"rotated":false,"trimmed":false},"landscapeTiles_005.png":{"frame":{"x":265,"y":1551,"w":132,"h":131},"spriteSourceSize":{"x":0,"y":0,"w":132,"h":131},"sourceSize":{"w":132,"h":131},"rotated":false,"trimmed":false},"landscapeTiles_006.png":{"frame":{"x":265,"y":1947,"w":132,"h":99},"spriteSourceSize":{"x":0,"y":0,"w":132,"h":99},"sourceSize":{"w":132,"h":99},"rotated":false,"trimmed":false},"landscapeTiles_007.png":{"frame":{"x":265,"y":1864,"w":132,"h":83},"spriteSourceSize":{"x":0,"y":0,"w":132,"h":83},"sourceSize":{"w":132,"h":83},"rotated":false,"trimmed":false},"landscapeTiles_008.png":{"frame":{"x":266,"y":921,"w":132,"h":131},"spriteSourceSize":{"x":0,"y":0,"w":132,"h":131},"sourceSize":{"w":132,"h":131},"rotated":false,"trimmed":false},"landscapeTiles_009.png":{"frame":{"x":0,"y":281,"w":133,"h":99},"spriteSourceSize":{"x":0,"y":0,"w":133,"h":99},"sourceSize":{"w":133,"h":99},"rotated":false,"trimmed":false},"landscapeTiles_010.png":{"frame":{"x":397,"y":1183,"w":132,"h":83},"spriteSourceSize":{"x":0,"y":0,"w":132,"h":83},"sourceSize":{"w":132,"h":83},"rotated":false,"trimmed":false},"landscapeTiles_011.png":{"frame":{"x":662,"y":693,"w":132,"h":99},"spriteSourceSize":{"x":0,"y":0,"w":132,"h":99},"sourceSize":{"w":132,"h":99},"rotated":false,"trimmed":false},"landscapeTiles_012.png":{"frame":{"x":397,"y":1052,"w":132,"h":131},"spriteSourceSize":{"x":0,"y":0,"w":132,"h":131},"sourceSize":{"w":132,"h":131},"rotated":false,"trimmed":false},"landscapeTiles_013.png":{"frame":{"x":793,"y":1303,"w":132,"h":99},"spriteSourceSize":{"x":0,"y":0,"w":132,"h":99},"sourceSize":{"w":132,"h":99},"rotated":false,"trimmed":false},"landscapeTiles_014.png":{"frame":{"x":133,"y":380,"w":133,"h":83},"spriteSourceSize":{"x":0,"y":0,"w":133,"h":83},"sourceSize":{"w":133,"h":83},"rotated":false,"trimmed":false},"landscapeTiles_015.png":{"frame":{"x":793,"y":1204,"w":132,"h":99},"spriteSourceSize":{"x":0,"y":0,"w":132,"h":99},"sourceSize":{"w":132,"h":99},"rotated":false,"trimmed":false},"landscapeTiles_016.png":{"frame":{"x":793,"y":1121,"w":132,"h":83},"spriteSourceSize":{"x":0,"y":0,"w":132,"h":83},"sourceSize":{"w":132,"h":83},"rotated":false,"trimmed":false},"landscapeTiles_017.png":{"frame":{"x":793,"y":990,"w":132,"h":131},"spriteSourceSize":{"x":0,"y":0,"w":132,"h":131},"sourceSize":{"w":132,"h":131},"rotated":false,"trimmed":false},"landscapeTiles_018.png":{"frame":{"x":793,"y":891,"w":132,"h":99},"spriteSourceSize":{"x":0,"y":0,"w":132,"h":99},"sourceSize":{"w":132,"h":99},"rotated":false,"trimmed":false},"landscapeTiles_019.png":{"frame":{"x":0,"y":0,"w":133,"h":99},"spriteSourceSize":{"x":0,"y":0,"w":133,"h":99},"sourceSize":{"w":133,"h":99},"rotated":false,"trimmed":false},"landscapeTiles_020.png":{"frame":{"x":0,"y":99,"w":133,"h":83},"spriteSourceSize":{"x":0,"y":0,"w":133,"h":83},"sourceSize":{"w":133,"h":83},"rotated":false,"trimmed":false},"landscapeTiles_021.png":{"frame":{"x":662,"y":594,"w":132,"h":99},"spriteSourceSize":{"x":0,"y":0,"w":132,"h":99},"sourceSize":{"w":132,"h":99},"rotated":false,"trimmed":false},"landscapeTiles_022.png":{"frame":{"x":662,"y":495,"w":132,"h":99},"spriteSourceSize":{"x":0,"y":0,"w":132,"h":99},"sourceSize":{"w":132,"h":99},"rotated":false,"trimmed":false},"landscapeTiles_023.png":{"frame":{"x":662,"y":396,"w":132,"h":99},"spriteSourceSize":{"x":0,"y":0,"w":132,"h":99},"sourceSize":{"w":132,"h":99},"rotated":false,"trimmed":false},"landscapeTiles_024.png":{"frame":{"x":662,"y":297,"w":132,"h":99},"spriteSourceSize":{"x":0,"y":0,"w":132,"h":99},"sourceSize":{"w":132,"h":99},"rotated":false,"trimmed":false},"landscapeTiles_025.png":{"frame":{"x":662,"y":198,"w":132,"h":99},"spriteSourceSize":{"x":0,"y":0,"w":132,"h":99},"sourceSize":{"w":132,"h":99},"rotated":false,"trimmed":false},"landscapeTiles_026.png":{"frame":{"x":0,"y":380,"w":133,"h":99},"spriteSourceSize":{"x":0,"y":0,"w":133,"h":99},"sourceSize":{"w":133,"h":99},"rotated":false,"trimmed":false},"landscapeTiles_027.png":{"frame":{"x":0,"y":1948,"w":133,"h":99},"spriteSourceSize":{"x":0,"y":0,"w":133,"h":99},"sourceSize":{"w":133,"h":99},"rotated":false,"trimmed":false},"landscapeTiles_028.png":{"frame":{"x":661,"y":1946,"w":132,"h":99},"spriteSourceSize":{"x":0,"y":0,"w":132,"h":99},"sourceSize":{"w":132,"h":99},"rotated":false,"trimmed":false},"landscapeTiles_029.png":{"frame":{"x":661,"y":1847,"w":132,"h":99},"spriteSourceSize":{"x":0,"y":0,"w":132,"h":99},"sourceSize":{"w":132,"h":99},"rotated":false,"trimmed":false},"landscapeTiles_030.png":{"frame":{"x":661,"y":1748,"w":132,"h":99},"spriteSourceSize":{"x":0,"y":0,"w":132,"h":99},"sourceSize":{"w":132,"h":99},"rotated":false,"trimmed":false},"landscapeTiles_031.png":{"frame":{"x":661,"y":1649,"w":132,"h":99},"spriteSourceSize":{"x":0,"y":0,"w":132,"h":99},"sourceSize":{"w":132,"h":99},"rotated":false,"trimmed":false},"landscapeTiles_032.png":{"frame":{"x":661,"y":1550,"w":132,"h":99},"spriteSourceSize":{"x":0,"y":0,"w":132,"h":99},"sourceSize":{"w":132,"h":99},"rotated":false,"trimmed":false},"landscapeTiles_033.png":{"frame":{"x":0,"y":1849,"w":133,"h":99},"spriteSourceSize":{"x":0,"y":0,"w":133,"h":99},"sourceSize":{"w":133,"h":99},"rotated":false,"trimmed":false},"landscapeTiles_034.png":{"frame":{"x":0,"y":1552,"w":133,"h":99},"spriteSourceSize":{"x":0,"y":0,"w":133,"h":99},"sourceSize":{"w":133,"h":99},"rotated":false,"trimmed":false},"landscapeTiles_035.png":{"frame":{"x":661,"y":1269,"w":132,"h":83},"spriteSourceSize":{"x":0,"y":0,"w":132,"h":83},"sourceSize":{"w":132,"h":83},"rotated":false,"trimmed":false},"landscapeTiles_036.png":{"frame":{"x":661,"y":1138,"w":132,"h":131},"spriteSourceSize":{"x":0,"y":0,"w":132,"h":131},"sourceSize":{"w":132,"h":131},"rotated":false,"trimmed":false},"landscapeTiles_037.png":{"frame":{"x":661,"y":1055,"w":132,"h":83},"spriteSourceSize":{"x":0,"y":0,"w":132,"h":83},"sourceSize":{"w":132,"h":83},"rotated":false,"trimmed":false},"landscapeTiles_038.png":{"frame":{"x":661,"y":956,"w":132,"h":99},"spriteSourceSize":{"x":0,"y":0,"w":132,"h":99},"sourceSize":{"w":132,"h":99},"rotated":false,"trimmed":false},"landscapeTiles_039.png":{"frame":{"x":530,"y":857,"w":132,"h":99},"spriteSourceSize":{"x":0,"y":0,"w":132,"h":99},"sourceSize":{"w":132,"h":99},"rotated":false,"trimmed":false},"landscapeTiles_040.png":{"frame":{"x":530,"y":758,"w":132,"h":99},"spriteSourceSize":{"x":0,"y":0,"w":132,"h":99},"sourceSize":{"w":132,"h":99},"rotated":false,"trimmed":false},"landscapeTiles_041.png":{"frame":{"x":133,"y":0,"w":133,"h":99},"spriteSourceSize":{"x":0,"y":0,"w":133,"h":99},"sourceSize":{"w":133,"h":99},"rotated":false,"trimmed":false},"landscapeTiles_042.png":{"frame":{"x":133,"y":198,"w":133,"h":83},"spriteSourceSize":{"x":0,"y":0,"w":133,"h":83},"sourceSize":{"w":133,"h":83},"rotated":false,"trimmed":false},"landscapeTiles_043.png":{"frame":{"x":530,"y":461,"w":132,"h":99},"spriteSourceSize":{"x":0,"y":0,"w":132,"h":99},"sourceSize":{"w":132,"h":99},"rotated":false,"trimmed":false},"landscapeTiles_044.png":{"frame":{"x":530,"y":378,"w":132,"h":83},"spriteSourceSize":{"x":0,"y":0,"w":132,"h":83},"sourceSize":{"w":132,"h":83},"rotated":false,"trimmed":false},"landscapeTiles_045.png":{"frame":{"x":530,"y":295,"w":132,"h":83},"spriteSourceSize":{"x":0,"y":0,"w":132,"h":83},"sourceSize":{"w":132,"h":83},"rotated":false,"trimmed":false},"landscapeTiles_046.png":{"frame":{"x":530,"y":198,"w":132,"h":97},"spriteSourceSize":{"x":0,"y":0,"w":132,"h":97},"sourceSize":{"w":132,"h":97},"rotated":false,"trimmed":false},"landscapeTiles_047.png":{"frame":{"x":530,"y":99,"w":132,"h":99},"spriteSourceSize":{"x":0,"y":0,"w":132,"h":99},"sourceSize":{"w":132,"h":99},"rotated":false,"trimmed":false},"landscapeTiles_048.png":{"frame":{"x":0,"y":479,"w":133,"h":99},"spriteSourceSize":{"x":0,"y":0,"w":133,"h":99},"sourceSize":{"w":133,"h":99},"rotated":false,"trimmed":false},"landscapeTiles_049.png":{"frame":{"x":0,"y":578,"w":133,"h":99},"spriteSourceSize":{"x":0,"y":0,"w":133,"h":99},"sourceSize":{"w":133,"h":99},"rotated":false,"trimmed":false},"landscapeTiles_050.png":{"frame":{"x":529,"y":1834,"w":132,"h":99},"spriteSourceSize":{"x":0,"y":0,"w":132,"h":99},"sourceSize":{"w":132,"h":99},"rotated":false,"trimmed":false},"landscapeTiles_051.png":{"frame":{"x":529,"y":1751,"w":132,"h":83},"spriteSourceSize":{"x":0,"y":0,"w":132,"h":83},"sourceSize":{"w":132,"h":83},"rotated":false,"trimmed":false},"landscapeTiles_052.png":{"frame":{"x":529,"y":1668,"w":132,"h":83},"spriteSourceSize":{"x":0,"y":0,"w":132,"h":83},"sourceSize":{"w":132,"h":83},"rotated":false,"trimmed":false},"landscapeTiles_053.png":{"frame":{"x":529,"y":1585,"w":132,"h":83},"spriteSourceSize":{"x":0,"y":0,"w":132,"h":83},"sourceSize":{"w":132,"h":83},"rotated":false,"trimmed":false},"landscapeTiles_054.png":{"frame":{"x":529,"y":1488,"w":132,"h":97},"spriteSourceSize":{"x":0,"y":0,"w":132,"h":97},"sourceSize":{"w":132,"h":97},"rotated":false,"trimmed":false},"landscapeTiles_055.png":{"frame":{"x":529,"y":1389,"w":132,"h":99},"spriteSourceSize":{"x":0,"y":0,"w":132,"h":99},"sourceSize":{"w":132,"h":99},"rotated":false,"trimmed":false},"landscapeTiles_056.png":{"frame":{"x":0,"y":677,"w":133,"h":83},"spriteSourceSize":{"x":0,"y":0,"w":133,"h":83},"sourceSize":{"w":133,"h":83},"rotated":false,"trimmed":false},"landscapeTiles_057.png":{"frame":{"x":0,"y":760,"w":133,"h":99},"spriteSourceSize":{"x":0,"y":0,"w":133,"h":99},"sourceSize":{"w":133,"h":99},"rotated":false,"trimmed":false},"landscapeTiles_058.png":{"frame":{"x":529,"y":1108,"w":132,"h":83},"spriteSourceSize":{"x":0,"y":0,"w":132,"h":83},"sourceSize":{"w":132,"h":83},"rotated":false,"trimmed":false},"landscapeTiles_059.png":{"frame":{"x":529,"y":1009,"w":132,"h":99},"spriteSourceSize":{"x":0,"y":0,"w":132,"h":99},"sourceSize":{"w":132,"h":99},"rotated":false,"trimmed":false},"landscapeTiles_060.png":{"frame":{"x":398,"y":926,"w":132,"h":83},"spriteSourceSize":{"x":0,"y":0,"w":132,"h":83},"sourceSize":{"w":132,"h":83},"rotated":false,"trimmed":false},"landscapeTiles_061.png":{"frame":{"x":398,"y":843,"w":132,"h":83},"spriteSourceSize":{"x":0,"y":0,"w":132,"h":83},"sourceSize":{"w":132,"h":83},"rotated":false,"trimmed":false},"landscapeTiles_062.png":{"frame":{"x":398,"y":744,"w":132,"h":99},"spriteSourceSize":{"x":0,"y":0,"w":132,"h":99},"sourceSize":{"w":132,"h":99},"rotated":false,"trimmed":false},"landscapeTiles_063.png":{"frame":{"x":0,"y":958,"w":133,"h":99},"spriteSourceSize":{"x":0,"y":0,"w":133,"h":99},"sourceSize":{"w":133,"h":99},"rotated":false,"trimmed":false},"landscapeTiles_064.png":{"frame":{"x":0,"y":1057,"w":133,"h":99},"spriteSourceSize":{"x":0,"y":0,"w":133,"h":99},"sourceSize":{"w":133,"h":99},"rotated":false,"trimmed":false},"landscapeTiles_065.png":{"frame":{"x":398,"y":447,"w":132,"h":99},"spriteSourceSize":{"x":0,"y":0,"w":132,"h":99},"sourceSize":{"w":132,"h":99},"rotated":false,"trimmed":false},"landscapeTiles_066.png":{"frame":{"x":398,"y":364,"w":132,"h":83},"spriteSourceSize":{"x":0,"y":0,"w":132,"h":83},"sourceSize":{"w":132,"h":83},"rotated":false,"trimmed":false},"landscapeTiles_067.png":{"frame":{"x":398,"y":265,"w":132,"h":99},"spriteSourceSize":{"x":0,"y":0,"w":132,"h":99},"sourceSize":{"w":132,"h":99},"rotated":false,"trimmed":false},"landscapeTiles_068.png":{"frame":{"x":398,"y":166,"w":132,"h":99},"spriteSourceSize":{"x":0,"y":0,"w":132,"h":99},"sourceSize":{"w":132,"h":99},"rotated":false,"trimmed":false},"landscapeTiles_069.png":{"frame":{"x":398,"y":83,"w":132,"h":83},"spriteSourceSize":{"x":0,"y":0,"w":132,"h":83},"sourceSize":{"w":132,"h":83},"rotated":false,"trimmed":false},"landscapeTiles_070.png":{"frame":{"x":398,"y":0,"w":132,"h":83},"spriteSourceSize":{"x":0,"y":0,"w":132,"h":83},"sourceSize":{"w":132,"h":83},"rotated":false,"trimmed":false},"landscapeTiles_071.png":{"frame":{"x":0,"y":1156,"w":133,"h":99},"spriteSourceSize":{"x":0,"y":0,"w":133,"h":99},"sourceSize":{"w":133,"h":99},"rotated":false,"trimmed":false},"landscapeTiles_072.png":{"frame":{"x":0,"y":1255,"w":133,"h":99},"spriteSourceSize":{"x":0,"y":0,"w":133,"h":99},"sourceSize":{"w":133,"h":99},"rotated":false,"trimmed":false},"landscapeTiles_073.png":{"frame":{"x":397,"y":1745,"w":132,"h":83},"spriteSourceSize":{"x":0,"y":0,"w":132,"h":83},"sourceSize":{"w":132,"h":83},"rotated":false,"trimmed":false},"landscapeTiles_074.png":{"frame":{"x":397,"y":1646,"w":132,"h":99},"spriteSourceSize":{"x":0,"y":0,"w":132,"h":99},"sourceSize":{"w":132,"h":99},"rotated":false,"trimmed":false},"landscapeTiles_075.png":{"frame":{"x":397,"y":1547,"w":132,"h":99},"spriteSourceSize":{"x":0,"y":0,"w":132,"h":99},"sourceSize":{"w":132,"h":99},"rotated":false,"trimmed":false},"landscapeTiles_076.png":{"frame":{"x":397,"y":1464,"w":132,"h":83},"spriteSourceSize":{"x":0,"y":0,"w":132,"h":83},"sourceSize":{"w":132,"h":83},"rotated":false,"trimmed":false},"landscapeTiles_077.png":{"frame":{"x":793,"y":1402,"w":132,"h":83},"spriteSourceSize":{"x":0,"y":0,"w":132,"h":83},"sourceSize":{"w":132,"h":83},"rotated":false,"trimmed":false},"landscapeTiles_078.png":{"frame":{"x":133,"y":760,"w":133,"h":99},"spriteSourceSize":{"x":0,"y":0,"w":133,"h":99},"sourceSize":{"w":133,"h":99},"rotated":false,"trimmed":false},"landscapeTiles_079.png":{"frame":{"x":0,"y":182,"w":133,"h":99},"spriteSourceSize":{"x":0,"y":0,"w":133,"h":99},"sourceSize":{"w":133,"h":99},"rotated":false,"trimmed":false},"landscapeTiles_080.png":{"frame":{"x":662,"y":792,"w":132,"h":99},"spriteSourceSize":{"x":0,"y":0,"w":132,"h":99},"sourceSize":{"w":132,"h":99},"rotated":false,"trimmed":false},"landscapeTiles_081.png":{"frame":{"x":662,"y":0,"w":132,"h":99},"spriteSourceSize":{"x":0,"y":0,"w":132,"h":99},"sourceSize":{"w":132,"h":99},"rotated":false,"trimmed":false},"landscapeTiles_082.png":{"frame":{"x":662,"y":99,"w":132,"h":99},"spriteSourceSize":{"x":0,"y":0,"w":132,"h":99},"sourceSize":{"w":132,"h":99},"rotated":false,"trimmed":false},"landscapeTiles_083.png":{"frame":{"x":266,"y":723,"w":132,"h":99},"spriteSourceSize":{"x":0,"y":0,"w":132,"h":99},"sourceSize":{"w":132,"h":99},"rotated":false,"trimmed":false},"landscapeTiles_084.png":{"frame":{"x":661,"y":1451,"w":132,"h":99},"spriteSourceSize":{"x":0,"y":0,"w":132,"h":99},"sourceSize":{"w":132,"h":99},"rotated":false,"trimmed":false},"landscapeTiles_085.png":{"frame":{"x":661,"y":1352,"w":132,"h":99},"spriteSourceSize":{"x":0,"y":0,"w":132,"h":99},"sourceSize":{"w":132,"h":99},"rotated":false,"trimmed":false},"landscapeTiles_086.png":{"frame":{"x":0,"y":1651,"w":133,"h":99},"spriteSourceSize":{"x":0,"y":0,"w":133,"h":99},"sourceSize":{"w":133,"h":99},"rotated":false,"trimmed":false},"landscapeTiles_087.png":{"frame":{"x":133,"y":281,"w":133,"h":99},"spriteSourceSize":{"x":0,"y":0,"w":133,"h":99},"sourceSize":{"w":133,"h":99},"rotated":false,"trimmed":false},"landscapeTiles_088.png":{"frame":{"x":530,"y":659,"w":132,"h":99},"spriteSourceSize":{"x":0,"y":0,"w":132,"h":99},"sourceSize":{"w":132,"h":99},"rotated":false,"trimmed":false},"landscapeTiles_089.png":{"frame":{"x":530,"y":560,"w":132,"h":99},"spriteSourceSize":{"x":0,"y":0,"w":132,"h":99},"sourceSize":{"w":132,"h":99},"rotated":false,"trimmed":false},"landscapeTiles_090.png":{"frame":{"x":266,"y":0,"w":132,"h":99},"spriteSourceSize":{"x":0,"y":0,"w":132,"h":99},"sourceSize":{"w":132,"h":99},"rotated":false,"trimmed":false},"landscapeTiles_091.png":{"frame":{"x":529,"y":1933,"w":132,"h":99},"spriteSourceSize":{"x":0,"y":0,"w":132,"h":99},"sourceSize":{"w":132,"h":99},"rotated":false,"trimmed":false},"landscapeTiles_092.png":{"frame":{"x":530,"y":0,"w":132,"h":99},"spriteSourceSize":{"x":0,"y":0,"w":132,"h":99},"sourceSize":{"w":132,"h":99},"rotated":false,"trimmed":false},"landscapeTiles_093.png":{"frame":{"x":133,"y":958,"w":133,"h":99},"spriteSourceSize":{"x":0,"y":0,"w":133,"h":99},"sourceSize":{"w":133,"h":99},"rotated":false,"trimmed":false},"landscapeTiles_094.png":{"frame":{"x":0,"y":859,"w":133,"h":99},"spriteSourceSize":{"x":0,"y":0,"w":133,"h":99},"sourceSize":{"w":133,"h":99},"rotated":false,"trimmed":false},"landscapeTiles_095.png":{"frame":{"x":529,"y":1290,"w":132,"h":99},"spriteSourceSize":{"x":0,"y":0,"w":132,"h":99},"sourceSize":{"w":132,"h":99},"rotated":false,"trimmed":false},"landscapeTiles_096.png":{"frame":{"x":398,"y":546,"w":132,"h":99},"spriteSourceSize":{"x":0,"y":0,"w":132,"h":99},"sourceSize":{"w":132,"h":99},"rotated":false,"trimmed":false},"landscapeTiles_097.png":{"frame":{"x":398,"y":645,"w":132,"h":99},"spriteSourceSize":{"x":0,"y":0,"w":132,"h":99},"sourceSize":{"w":132,"h":99},"rotated":false,"trimmed":false},"landscapeTiles_098.png":{"frame":{"x":265,"y":1238,"w":132,"h":131},"spriteSourceSize":{"x":0,"y":0,"w":132,"h":131},"sourceSize":{"w":132,"h":131},"rotated":false,"trimmed":false},"landscapeTiles_099.png":{"frame":{"x":397,"y":1828,"w":132,"h":99},"spriteSourceSize":{"x":0,"y":0,"w":132,"h":99},"sourceSize":{"w":132,"h":99},"rotated":false,"trimmed":false},"landscapeTiles_100.png":{"frame":{"x":397,"y":1927,"w":132,"h":99},"spriteSourceSize":{"x":0,"y":0,"w":132,"h":99},"sourceSize":{"w":132,"h":99},"rotated":false,"trimmed":false},"landscapeTiles_101.png":{"frame":{"x":0,"y":1453,"w":133,"h":99},"spriteSourceSize":{"x":0,"y":0,"w":133,"h":99},"sourceSize":{"w":133,"h":99},"rotated":false,"trimmed":false},"landscapeTiles_102.png":{"frame":{"x":0,"y":1354,"w":133,"h":99},"spriteSourceSize":{"x":0,"y":0,"w":133,"h":99},"sourceSize":{"w":133,"h":99},"rotated":false,"trimmed":false},"landscapeTiles_103.png":{"frame":{"x":266,"y":822,"w":132,"h":99},"spriteSourceSize":{"x":0,"y":0,"w":132,"h":99},"sourceSize":{"w":132,"h":99},"rotated":false,"trimmed":false},"landscapeTiles_104.png":{"frame":{"x":266,"y":624,"w":132,"h":99},"spriteSourceSize":{"x":0,"y":0,"w":132,"h":99},"sourceSize":{"w":132,"h":99},"rotated":false,"trimmed":false},"landscapeTiles_105.png":{"frame":{"x":266,"y":525,"w":132,"h":99},"spriteSourceSize":{"x":0,"y":0,"w":132,"h":99},"sourceSize":{"w":132,"h":99},"rotated":false,"trimmed":false},"landscapeTiles_106.png":{"frame":{"x":133,"y":1844,"w":132,"h":131},"spriteSourceSize":{"x":0,"y":0,"w":132,"h":131},"sourceSize":{"w":132,"h":131},"rotated":false,"trimmed":false},"landscapeTiles_107.png":{"frame":{"x":133,"y":859,"w":133,"h":99},"spriteSourceSize":{"x":0,"y":0,"w":133,"h":99},"sourceSize":{"w":133,"h":99},"rotated":false,"trimmed":false},"landscapeTiles_108.png":{"frame":{"x":133,"y":661,"w":133,"h":99},"spriteSourceSize":{"x":0,"y":0,"w":133,"h":99},"sourceSize":{"w":133,"h":99},"rotated":false,"trimmed":false},"landscapeTiles_109.png":{"frame":{"x":133,"y":1057,"w":132,"h":131},"spriteSourceSize":{"x":0,"y":0,"w":132,"h":131},"sourceSize":{"w":132,"h":131},"rotated":false,"trimmed":false},"landscapeTiles_110.png":{"frame":{"x":133,"y":1188,"w":132,"h":99},"spriteSourceSize":{"x":0,"y":0,"w":132,"h":99},"sourceSize":{"w":132,"h":99},"rotated":false,"trimmed":false},"landscapeTiles_111.png":{"frame":{"x":133,"y":1515,"w":132,"h":99},"spriteSourceSize":{"x":0,"y":0,"w":132,"h":99},"sourceSize":{"w":132,"h":99},"rotated":false,"trimmed":false},"landscapeTiles_112.png":{"frame":{"x":133,"y":1287,"w":132,"h":99},"spriteSourceSize":{"x":0,"y":0,"w":132,"h":99},"sourceSize":{"w":132,"h":99},"rotated":false,"trimmed":false},"landscapeTiles_113.png":{"frame":{"x":133,"y":562,"w":133,"h":99},"spriteSourceSize":{"x":0,"y":0,"w":133,"h":99},"sourceSize":{"w":133,"h":99},"rotated":false,"trimmed":false},"landscapeTiles_114.png":{"frame":{"x":133,"y":463,"w":133,"h":99},"spriteSourceSize":{"x":0,"y":0,"w":133,"h":99},"sourceSize":{"w":133,"h":99},"rotated":false,"trimmed":false},"landscapeTiles_115.png":{"frame":{"x":133,"y":1713,"w":132,"h":131},"spriteSourceSize":{"x":0,"y":0,"w":132,"h":131},"sourceSize":{"w":132,"h":131},"rotated":false,"trimmed":false},"landscapeTiles_116.png":{"frame":{"x":266,"y":99,"w":132,"h":99},"spriteSourceSize":{"x":0,"y":0,"w":132,"h":99},"sourceSize":{"w":132,"h":99},"rotated":false,"trimmed":false},"landscapeTiles_117.png":{"frame":{"x":133,"y":1614,"w":132,"h":99},"spriteSourceSize":{"x":0,"y":0,"w":132,"h":99},"sourceSize":{"w":132,"h":99},"rotated":false,"trimmed":false},"landscapeTiles_118.png":{"frame":{"x":133,"y":99,"w":133,"h":99},"spriteSourceSize":{"x":0,"y":0,"w":133,"h":99},"sourceSize":{"w":133,"h":99},"rotated":false,"trimmed":false},"landscapeTiles_119.png":{"frame":{"x":265,"y":1765,"w":132,"h":99},"spriteSourceSize":{"x":0,"y":0,"w":132,"h":99},"sourceSize":{"w":132,"h":99},"rotated":false,"trimmed":false},"landscapeTiles_120.png":{"frame":{"x":266,"y":297,"w":132,"h":129},"spriteSourceSize":{"x":0,"y":0,"w":132,"h":129},"sourceSize":{"w":132,"h":129},"rotated":false,"trimmed":false},"landscapeTiles_121.png":{"frame":{"x":266,"y":426,"w":132,"h":99},"spriteSourceSize":{"x":0,"y":0,"w":132,"h":99},"sourceSize":{"w":132,"h":99},"rotated":false,"trimmed":false},"landscapeTiles_122.png":{"frame":{"x":0,"y":1750,"w":133,"h":99},"spriteSourceSize":{"x":0,"y":0,"w":133,"h":99},"sourceSize":{"w":133,"h":99},"rotated":false,"trimmed":false},"landscapeTiles_123.png":{"frame":{"x":266,"y":198,"w":132,"h":99},"spriteSourceSize":{"x":0,"y":0,"w":132,"h":99},"sourceSize":{"w":132,"h":99},"rotated":false,"trimmed":false},"landscapeTiles_124.png":{"frame":{"x":133,"y":1386,"w":132,"h":129},"spriteSourceSize":{"x":0,"y":0,"w":132,"h":129},"sourceSize":{"w":132,"h":129},"rotated":false,"trimmed":false},"landscapeTiles_125.png":{"frame":{"x":397,"y":1266,"w":132,"h":99},"spriteSourceSize":{"x":0,"y":0,"w":132,"h":99},"sourceSize":{"w":132,"h":99},"rotated":false,"trimmed":false},"landscapeTiles_126.png":{"frame":{"x":397,"y":1365,"w":132,"h":99},"spriteSourceSize":{"x":0,"y":0,"w":132,"h":99},"sourceSize":{"w":132,"h":99},"rotated":false,"trimmed":false},"landscapeTiles_127.png":{"frame":{"x":265,"y":1140,"w":132,"h":98},"spriteSourceSize":{"x":0,"y":0,"w":132,"h":98},"sourceSize":{"w":132,"h":98},"rotated":false,"trimmed":false}},"meta":{"app":"TextureAtlasConverter","version":1,"sprites":128,"image":"sheet.png"}}